ick/__init__.py
ick/__main__.py
ick/_regex_translate.py
ick/add_rule.py
ick/base_rule.py
ick/cmdline.py
ick/git.py
ick/git_diff.py
ick/project_finder.py
ick/runner.py
ick/sh.py
ick/types_project.py
ick/util.py
ick/venv.py
ick/config/__init__.py
ick/config/main.py
ick/config/rule_repo.py
ick/config/rules.py
ick/config/search.py
ick/config/settings.py
ick/rules/__init__.py
ick/rules/ast_grep.py
ick/rules/docker.py
ick/rules/merge_toml.py
ick/rules/pygrep.py
ick/rules/python.py
ick/rules/shell.py
ick-0.7.0.dist-info/licenses/LICENSE
ick_protocol/__init__.py
ick_protocol/ick_protocol.py
ick-0.7.0.dist-info/METADATA
ick-0.7.0.dist-info/WHEEL
ick-0.7.0.dist-info/entry_points.txt
ick-0.7.0.dist-info/top_level.txt
ick-0.7.0.dist-info/RECORD
