Metadata-Version: 2.4
Name: ick
Version: 0.7.0
Summary: Applier of fine source code fixes since 2025
Home-page: https://github.com/advice-animal/ick/
Author: Tim Hatch
Author-email: tim@timhatch.com
License: MIT
Project-URL: Documentation, https://ick.readthedocs.io
Project-URL: Source, https://github.com/advice-animal/ick
Requires-Python: >=3.11
License-File: LICENSE
Requires-Dist: click
Requires-Dist: filelock
Requires-Dist: keke
Requires-Dist: msgspec==0.19.0
Requires-Dist: platformdirs
Requires-Dist: rich==13.*
Requires-Dist: uv==0.6.*
Requires-Dist: vmodule
Requires-Dist: tomlkit
Requires-Dist: moreorless>=0.5.0
Requires-Dist: feedforward>=0.8.0
Provides-Extra: dev
Requires-Dist: ruff==0.12.0; extra == "dev"
Requires-Dist: mypy==1.16.1; extra == "dev"
Requires-Dist: checkdeps; extra == "dev"
Provides-Extra: docs
Requires-Dist: cogapp; extra == "docs"
Requires-Dist: sphinx==8.1.3; extra == "docs"
Requires-Dist: sphinx-mdinclude==0.6.2; extra == "docs"
Requires-Dist: sphinx-inline-tabs; extra == "docs"
Requires-Dist: furo; extra == "docs"
Provides-Extra: test
Requires-Dist: pytest-cov; extra == "test"
Requires-Dist: pytest-mock; extra == "test"
Requires-Dist: pytest==8.*; extra == "test"
Dynamic: license-file
